{"total_count":5,"workflow_runs":[{"id":21797936997,"name":"CI","node_id":"WFR_kwLORKfkM88AAAAFE0IfZQ","head_branch":"master","head_sha":"bd539e7b7eb4545e281869ce5ff1725afd6f4ff1","path":".github/workflows/ci.yml","display_title":"ci: use mongosh in MongoDB health check (mongo:6.0)","run_number":14,"event":"push","status":"in_progress","conclusion":null,"workflow_id":231456082,"check_suite_id":56761699885,"check_suite_node_id":"CS_kwDORKfkM88AAAANN0LOLQ","url":"https://api.github.com/repos/RESMIND/VitiScanPRO_V3/actions/runs/21797936997","html_url":"https://github.com/RESMIND/VitiScanPRO_V3/actions/runs/21797936997","pull_requests":[],"created_at":"2026-02-08T12:12:02Z","updated_at":"2026-02-08T12:12:06Z","actor":{"login":"RESMIND","id":212447599,"node_id":"U_kgDODKmxbw","avatar_url":"https://avatars.githubusercontent.com/u/212447599?v=4","gravatar_id":"","url":"https://api.github.com/users/RESMIND","html_url":"https://github.com/RESMIND","followers_url":"https://api.github.com/users/RESMIND/followers","following_url":"https://api.github.com/users/RESMIND/following{/other_user}","gists_url":"https://api.github.com/users/RESMIND/gists{/gist_id}","starred_url":"https://api.github.com/users/RESMIND/starred{/owner}{/repo}","subscriptions_url":"https://api.github.com/users/RESMIND/subscriptions","organizations_url":"https://api.github.com/users/RESMIND/orgs","repos_url":"https://api.github.com/users/RESMIND/repos","events_url":"https://api.github.com/users/RESMIND/events{/privacy}","received_events_url":"https://api.github.com/users/RESMIND/received_events","type":"User","user_view_type":"public","site_admin":false},"run_attempt":1,"referenced_workflows":[],"run_started_at":"2026-02-08T12:12:02Z","triggering_actor":{"login":"RESMIND","id":212447599,"node_id":"U_kgDODKmxbw","avatar_url":"https://avatars.githubusercontent.com/u/212447599?v=4","gravatar_id":"","url":"https://api.github.com/users/RESMIND","html_url":"https://github.com/RESMIND","followers_url":"https://api.github.com/users/RESMIND/followers","following_url":"https://api.github.com/users/RESMIND/following{/other_user}","gists_url":"https://api.github.com/users/RESMIND/gists{/gist_id}","starred_url":"https://api.github.com/users/RESMIND/starred{/owner}{/repo}","subscriptions_url":"https://api.github.com/users/RESMIND/subscriptions","organizations_url":"https://api.github.com/users/RESMIND/orgs","repos_url":"https://api.github.com/users/RESMIND/repos","events_url":"https://api.github.com/users/RESMIND/events{/privacy}","received_events_url":"https://api.github.com/users/RESMIND/received_events","type":"User","user_view_type":"public","site_admin":false},"jobs_url":"https://api.github.com/repos/RESMIND/VitiScanPRO_V3/actions/runs/21797936997/jobs","logs_url":"https://api.github.com/repos/RESMIND/VitiScanPRO_V3/actions/runs/21797936997/logs","check_suite_url":"https://api.github.com/repos/RESMIND/VitiScanPRO_V3/check-suites/56761699885","artifacts_url":"https://api.github.com/repos/RESMIND/VitiScanPRO_V3/actions/runs/21797936997/artifacts","cancel_url":"https://api.github.com/repos/RESMIND/VitiScanPRO_V3/actions/runs/21797936997/cancel","rerun_url":"https://api.github.com/repos/RESMIND/VitiScanPRO_V3/actions/runs/21797936997/rerun","previous_attempt_url":null,"workflow_url":"https://api.github.com/repos/RESMIND/VitiScanPRO_V3/actions/workflows/231456082","head_commit":{"id":"bd539e7b7eb4545e281869ce5ff1725afd6f4ff1","tree_id":"9aeacbb7a0746928a0b9f00e4038d0d004710e25","message":"ci: use mongosh in MongoDB health check (mongo:6.0)","timestamp":"2026-02-08T12:11:57Z","author":{"name":"VitiScan Bot","email":"dev@vitiscan.local"},"committer":{"name":"VitiScan Bot","email":"dev@vitiscan.local"}},"repository":{"id":1151853619,"node_id":"R_kgDORKfkMw","name":"VitiScanPRO_V3","full_name":"RESMIND/VitiScanPRO_V3","private":false,"owner":{"login":"RESMIND","id":212447599,"node_id":"U_kgDODKmxbw","avatar_url":"https://avatars.githubusercontent.com/u/212447599?v=4","gravatar_id":"","url":"https://api.github.com/users/RESMIND","html_url":"https://github.com/RESMIND","followers_url":"https://api.github.com/users/RESMIND/followers","following_url":"https://api.github.com/users/RESMIND/following{/other_user}","gists_url":"https://api.github.com/users/RESMIND/gists{/gist_id}","starred_url":"https://api.github.com/users/RESMIND/starred{/owner}{/repo}","subscriptions_url":"https://api.github.com/users/RESMIND/subscriptions","organizations_url":"https://api.github.com/users/RESMIND/orgs","repos_url":"https://api.github.com/users/RESMIND/repos","events_url":"https://api.github.com/users/RESMIND/events{/privacy}","received_events_url":"https://api.github.com/users/RESMIND/received_events","type":"User","user_view_type":"public","site_admin":false},"html_url":"https://github.com/RESMIND/VitiScanPRO_V3","description":"Sync local changes cu repo-ul remote","fork":false,"url":"https://api.github.com/repos/RESMIND/VitiScanPRO_V3","forks_url":"https://api.github.com/repos/RESMIND/VitiScanPRO_V3/forks","keys_url":"https://api.github.com/repos/RESMIND/VitiScanPRO_V3/keys{/key_id}","collaborators_url":"https://api.github.com/repos/RESMIND/VitiScanPRO_V3/collaborators{/collaborator}","teams_url":"https://api.github.com/repos/RESMIND/VitiScanPRO_V3/teams","hooks_url":"https://api.github.com/repos/RESMIND/VitiScanPRO_V3/hooks","issue_events_url":"https://api.github.com/repos/RESMIND/VitiScanPRO_V3/issues/events{/number}","events_url":"https://api.github.com/repos/RESMIND/VitiScanPRO_V3/events","assignees_url":"https://api.github.com/repos/RESMIND/VitiScanPRO_V3/assignees{/user}","branches_url":"https://api.github.com/repos/RESMIND/VitiScanPRO_V3/branches{/branch}","tags_url":"https://api.github.com/repos/RESMIND/VitiScanPRO_V3/tags","blobs_url":"https://api.github.com/repos/RESMIND/VitiScanPRO_V3/git/blobs{/sha}","git_tags_url":"https://api.github.com/repos/RESMIND/VitiScanPRO_V3/git/tags{/sha}","git_refs_url":"https://api.github.com/repos/RESMIND/VitiScanPRO_V3/git/refs{/sha}","trees_url":"https://api.github.com/repos/RESMIND/VitiScanPRO_V3/git/trees{/sha}","statuses_url":"https://api.github.com/repos/RESMIND/VitiScanPRO_V3/statuses/{sha}","languages_url":"https://api.github.com/repos/RESMIND/VitiScanPRO_V3/languages","stargazers_url":"https://api.github.com/repos/RESMIND/VitiScanPRO_V3/stargazers","contributors_url":"https://api.github.com/repos/RESMIND/VitiScanPRO_V3/contributors","subscribers_url":"https://api.github.com/repos/RESMIND/VitiScanPRO_V3/subscribers","subscription_url":"https://api.github.com/repos/RESMIND/VitiScanPRO_V3/subscription","commits_url":"https://api.github.com/repos/RESMIND/VitiScanPRO_V3/commits{/sha}","git_commits_url":"https://api.github.com/repos/RESMIND/VitiScanPRO_V3/git/commits{/sha}","comments_url":"https://api.github.com/repos/RESMIND/VitiScanPRO_V3/comments{/number}","issue_comment_url":"https://api.github.com/repos/RESMIND/VitiScanPRO_V3/issues/comments{/number}","contents_url":"https://api.github.com/repos/RESMIND/VitiScanPRO_V3/contents/{+path}","compare_url":"https://api.github.com/repos/RESMIND/VitiScanPRO_V3/compare/{base}...{head}","merges_url":"https://api.github.com/repos/RESMIND/VitiScanPRO_V3/merges","archive_url":"https://api.github.com/repos/RESMIND/VitiScanPRO_V3/{archive_format}{/ref}","downloads_url":"https://api.github.com/repos/RESMIND/VitiScanPRO_V3/downloads","issues_url":"https://api.github.com/repos/RESMIND/VitiScanPRO_V3/issues{/number}","pulls_url":"https://api.github.com/repos/RESMIND/VitiScanPRO_V3/pulls{/number}","milestones_url":"https://api.github.com/repos/RESMIND/VitiScanPRO_V3/milestones{/number}","notifications_url":"https://api.github.com/repos/RESMIND/VitiScanPRO_V3/notifications{?since,all,participating}","labels_url":"https://api.github.com/repos/RESMIND/VitiScanPRO_V3/labels{/name}","releases_url":"https://api.github.com/repos/RESMIND/VitiScanPRO_V3/releases{/id}","deployments_url":"https://api.github.com/repos/RESMIND/VitiScanPRO_V3/deployments"},"head_repository":{"id":1151853619,"node_id":"R_kgDORKfkMw","name":"VitiScanPRO_V3","full_name":"RESMIND/VitiScanPRO_V3","private":false,"owner":{"login":"RESMIND","id":212447599,"node_id":"U_kgDODKmxbw","avatar_url":"https://avatars.githubusercontent.com/u/212447599?v=4","gravatar_id":"","url":"https://api.github.com/users/RESMIND","html_url":"https://github.com/RESMIND","followers_url":"https://api.github.com/users/RESMIND/followers","following_url":"https://api.github.com/users/RESMIND/following{/other_user}","gists_url":"https://api.github.com/users/RESMIND/gists{/gist_id}","starred_url":"https://api.github.com/users/RESMIND/starred{/owner}{/repo}","subscriptions_url":"https://api.github.com/users/RESMIND/subscriptions","organizations_url":"https://api.github.com/users/RESMIND/orgs","repos_url":"https://api.github.com/users/RESMIND/repos","events_url":"https://api.github.com/users/RESMIND/events{/privacy}","received_events_url":"https://api.github.com/users/RESMIND/received_events","type":"User","user_view_type":"public","site_admin":false},"html_url":"https://github.com/RESMIND/VitiScanPRO_V3","description":"Sync local changes cu repo-ul remote","fork":false,"url":"https://api.github.com/repos/RESMIND/VitiScanPRO_V3","forks_url":"https://api.github.com/repos/RESMIND/VitiScanPRO_V3/forks","keys_url":"https://api.github.com/repos/RESMIND/VitiScanPRO_V3/keys{/key_id}","collaborators_url":"https://api.github.com/repos/RESMIND/VitiScanPRO_V3/collaborators{/collaborator}","teams_url":"https://api.github.com/repos/RESMIND/VitiScanPRO_V3/teams","hooks_url":"https://api.github.com/repos/RESMIND/VitiScanPRO_V3/hooks","issue_events_url":"https://api.github.com/repos/RESMIND/VitiScanPRO_V3/issues/events{/number}","events_url":"https://api.github.com/repos/RESMIND/VitiScanPRO_V3/events","assignees_url":"https://api.github.com/repos/RESMIND/VitiScanPRO_V3/assignees{/user}","branches_url":"https://api.github.com/repos/RESMIND/VitiScanPRO_V3/branches{/branch}","tags_url":"https://api.github.com/repos/RESMIND/VitiScanPRO_V3/tags","blobs_url":"https://api.github.com/repos/RESMIND/VitiScanPRO_V3/git/blobs{/sha}","git_tags_url":"https://api.github.com/repos/RESMIND/VitiScanPRO_V3/git/tags{/sha}","git_refs_url":"https://api.github.com/repos/RESMIND/VitiScanPRO_V3/git/refs{/sha}","trees_url":"https://api.github.com/repos/RESMIND/VitiScanPRO_V3/git/trees{/sha}","statuses_url":"https://api.github.com/repos/RESMIND/VitiScanPRO_V3/statuses/{sha}","languages_url":"https://api.github.com/repos/RESMIND/VitiScanPRO_V3/languages","stargazers_url":"https://api.github.com/repos/RESMIND/VitiScanPRO_V3/stargazers","contributors_url":"https://api.github.com/repos/RESMIND/VitiScanPRO_V3/contributors","subscribers_url":"https://api.github.com/repos/RESMIND/VitiScanPRO_V3/subscribers","subscription_url":"https://api.github.com/repos/RESMIND/VitiScanPRO_V3/subscription","commits_url":"https://api.github.com/repos/RESMIND/VitiScanPRO_V3/commits{/sha}","git_commits_url":"https://api.github.com/repos/RESMIND/VitiScanPRO_V3/git/commits{/sha}","comments_url":"https://api.github.com/repos/RESMIND/VitiScanPRO_V3/comments{/number}","issue_comment_url":"https://api.github.com/repos/RESMIND/VitiScanPRO_V3/issues/comments{/number}","contents_url":"https://api.github.com/repos/RESMIND/VitiScanPRO_V3/contents/{+path}","compare_url":"https://api.github.com/repos/RESMIND/VitiScanPRO_V3/compare/{base}...{head}","merges_url":"https://api.github.com/repos/RESMIND/VitiScanPRO_V3/merges","archive_url":"https://api.github.com/repos/RESMIND/VitiScanPRO_V3/{archive_format}{/ref}","downloads_url":"https://api.github.com/repos/RESMIND/VitiScanPRO_V3/downloads","issues_url":"https://api.github.com/repos/RESMIND/VitiScanPRO_V3/issues{/number}","pulls_url":"https://api.github.com/repos/RESMIND/VitiScanPRO_V3/pulls{/number}","milestones_url":"https://api.github.com/repos/RESMIND/VitiScanPRO_V3/milestones{/number}","notifications_url":"https://api.github.com/repos/RESMIND/VitiScanPRO_V3/notifications{?since,all,participating}","labels_url":"https://api.github.com/repos/RESMIND/VitiScanPRO_V3/labels{/name}","releases_url":"https://api.github.com/repos/RESMIND/VitiScanPRO_V3/releases{/id}","deployments_url":"https://api.github.com/repos/RESMIND/VitiScanPRO_V3/deployments"}},{"id":21797878778,"name":"CI","node_id":"WFR_kwLORKfkM88AAAAFE0E7-g","head_branch":"master","head_sha":"60a757d7411a3318763388e82d5316b32f0c1ba2","path":".github/workflows/ci.yml","display_title":"ci: ensure pymongo installed before MongoDB health check","run_number":13,"event":"push","status":"completed","conclusion":"failure","workflow_id":231456082,"check_suite_id":56761539546,"check_suite_node_id":"CS_kwDORKfkM88AAAANN0Bb2g","url":"https://api.github.com/repos/RESMIND/VitiScanPRO_V3/actions/runs/21797878778","html_url":"https://github.com/RESMIND/VitiScanPRO_V3/actions/runs/21797878778","pull_requests":[],"created_at":"2026-02-08T12:07:38Z","updated_at":"2026-02-08T12:08:58Z","actor":{"login":"RESMIND","id":212447599,"node_id":"U_kgDODKmxbw","avatar_url":"https://avatars.githubusercontent.com/u/212447599?v=4","gravatar_id":"","url":"https://api.github.com/users/RESMIND","html_url":"https://github.com/RESMIND","followers_url":"https://api.github.com/users/RESMIND/followers","following_url":"https://api.github.com/users/RESMIND/following{/other_user}","gists_url":"https://api.github.com/users/RESMIND/gists{/gist_id}","starred_url":"https://api.github.com/users/RESMIND/starred{/owner}{/repo}","subscriptions_url":"https://api.github.com/users/RESMIND/subscriptions","organizations_url":"https://api.github.com/users/RESMIND/orgs","repos_url":"https://api.github.com/users/RESMIND/repos","events_url":"https://api.github.com/users/RESMIND/events{/privacy}","received_events_url":"https://api.github.com/users/RESMIND/received_events","type":"User","user_view_type":"public","site_admin":false},"run_attempt":1,"referenced_workflows":[],"run_started_at":"2026-02-08T12:07:38Z","triggering_actor":{"login":"RESMIND","id":212447599,"node_id":"U_kgDODKmxbw","avatar_url":"https://avatars.githubusercontent.com/u/212447599?v=4","gravatar_id":"","url":"https://api.github.com/users/RESMIND","html_url":"https://github.com/RESMIND","followers_url":"https://api.github.com/users/RESMIND/followers","following_url":"https://api.github.com/users/RESMIND/following{/other_user}","gists_url":"https://api.github.com/users/RESMIND/gists{/gist_id}","starred_url":"https://api.github.com/users/RESMIND/starred{/owner}{/repo}","subscriptions_url":"https://api.github.com/users/RESMIND/subscriptions","organizations_url":"https://api.github.com/users/RESMIND/orgs","repos_url":"https://api.github.com/users/RESMIND/repos","events_url":"https://api.github.com/users/RESMIND/events{/privacy}","received_events_url":"https://api.github.com/users/RESMIND/received_events","type":"User","user_view_type":"public","site_admin":false},"jobs_url":"https://api.github.com/repos/RESMIND/VitiScanPRO_V3/actions/runs/21797878778/jobs","logs_url":"https://api.github.com/repos/RESMIND/VitiScanPRO_V3/actions/runs/21797878778/logs","check_suite_url":"https://api.github.com/repos/RESMIND/VitiScanPRO_V3/check-suites/56761539546","artifacts_url":"https://api.github.com/repos/RESMIND/VitiScanPRO_V3/actions/runs/21797878778/artifacts","cancel_url":"https://api.github.com/repos/RESMIND/VitiScanPRO_V3/actions/runs/21797878778/cancel","rerun_url":"https://api.github.com/repos/RESMIND/VitiScanPRO_V3/actions/runs/21797878778/rerun","previous_attempt_url":null,"workflow_url":"https://api.github.com/repos/RESMIND/VitiScanPRO_V3/actions/workflows/231456082","head_commit":{"id":"60a757d7411a3318763388e82d5316b32f0c1ba2","tree_id":"1e23cd1c7c60dd8949f81d5d5fb3035213ad12d7","message":"ci: ensure pymongo installed before MongoDB health check","timestamp":"2026-02-08T12:07:34Z","author":{"name":"VitiScan Bot","email":"dev@vitiscan.local"},"committer":{"name":"VitiScan Bot","email":"dev@vitiscan.local"}},"repository":{"id":1151853619,"node_id":"R_kgDORKfkMw","name":"VitiScanPRO_V3","full_name":"RESMIND/VitiScanPRO_V3","private":false,"owner":{"login":"RESMIND","id":212447599,"node_id":"U_kgDODKmxbw","avatar_url":"https://avatars.githubusercontent.com/u/212447599?v=4","gravatar_id":"","url":"https://api.github.com/users/RESMIND","html_url":"https://github.com/RESMIND","followers_url":"https://api.github.com/users/RESMIND/followers","following_url":"https://api.github.com/users/RESMIND/following{/other_user}","gists_url":"https://api.github.com/users/RESMIND/gists{/gist_id}","starred_url":"https://api.github.com/users/RESMIND/starred{/owner}{/repo}","subscriptions_url":"https://api.github.com/users/RESMIND/subscriptions","organizations_url":"https://api.github.com/users/RESMIND/orgs","repos_url":"https://api.github.com/users/RESMIND/repos","events_url":"https://api.github.com/users/RESMIND/events{/privacy}","received_events_url":"https://api.github.com/users/RESMIND/received_events","type":"User","user_view_type":"public","site_admin":false},"html_url":"https://github.com/RESMIND/VitiScanPRO_V3","description":"Sync local changes cu repo-ul remote","fork":false,"url":"https://api.github.com/repos/RESMIND/VitiScanPRO_V3","forks_url":"https://api.github.com/repos/RESMIND/VitiScanPRO_V3/forks","keys_url":"https://api.github.com/repos/RESMIND/VitiScanPRO_V3/keys{/key_id}","collaborators_url":"https://api.github.com/repos/RESMIND/VitiScanPRO_V3/collaborators{/collaborator}","teams_url":"https://api.github.com/repos/RESMIND/VitiScanPRO_V3/teams","hooks_url":"https://api.github.com/repos/RESMIND/VitiScanPRO_V3/hooks","issue_events_url":"https://api.github.com/repos/RESMIND/VitiScanPRO_V3/issues/events{/number}","events_url":"https://api.github.com/repos/RESMIND/VitiScanPRO_V3/events","assignees_url":"https://api.github.com/repos/RESMIND/VitiScanPRO_V3/assignees{/user}","branches_url":"https://api.github.com/repos/RESMIND/VitiScanPRO_V3/branches{/branch}","tags_url":"https://api.github.com/repos/RESMIND/VitiScanPRO_V3/tags","blobs_url":"https://api.github.com/repos/RESMIND/VitiScanPRO_V3/git/blobs{/sha}","git_tags_url":"https://api.github.com/repos/RESMIND/VitiScanPRO_V3/git/tags{/sha}","git_refs_url":"https://api.github.com/repos/RESMIND/VitiScanPRO_V3/git/refs{/sha}","trees_url":"https://api.github.com/repos/RESMIND/VitiScanPRO_V3/git/trees{/sha}","statuses_url":"https://api.github.com/repos/RESMIND/VitiScanPRO_V3/statuses/{sha}","languages_url":"https://api.github.com/repos/RESMIND/VitiScanPRO_V3/languages","stargazers_url":"https://api.github.com/repos/RESMIND/VitiScanPRO_V3/stargazers","contributors_url":"https://api.github.com/repos/RESMIND/VitiScanPRO_V3/contributors","subscribers_url":"https://api.github.com/repos/RESMIND/VitiScanPRO_V3/subscribers","subscription_url":"https://api.github.com/repos/RESMIND/VitiScanPRO_V3/subscription","commits_url":"https://api.github.com/repos/RESMIND/VitiScanPRO_V3/commits{/sha}","git_commits_url":"https://api.github.com/repos/RESMIND/VitiScanPRO_V3/git/commits{/sha}","comments_url":"https://api.github.com/repos/RESMIND/VitiScanPRO_V3/comments{/number}","issue_comment_url":"https://api.github.com/repos/RESMIND/VitiScanPRO_V3/issues/comments{/number}","contents_url":"https://api.github.com/repos/RESMIND/VitiScanPRO_V3/contents/{+path}","compare_url":"https://api.github.com/repos/RESMIND/VitiScanPRO_V3/compare/{base}...{head}","merges_url":"https://api.github.com/repos/RESMIND/VitiScanPRO_V3/merges","archive_url":"https://api.github.com/repos/RESMIND/VitiScanPRO_V3/{archive_format}{/ref}","downloads_url":"https://api.github.com/repos/RESMIND/VitiScanPRO_V3/downloads","issues_url":"https://api.github.com/repos/RESMIND/VitiScanPRO_V3/issues{/number}","pulls_url":"https://api.github.com/repos/RESMIND/VitiScanPRO_V3/pulls{/number}","milestones_url":"https://api.github.com/repos/RESMIND/VitiScanPRO_V3/milestones{/number}","notifications_url":"https://api.github.com/repos/RESMIND/VitiScanPRO_V3/notifications{?since,all,participating}","labels_url":"https://api.github.com/repos/RESMIND/VitiScanPRO_V3/labels{/name}","releases_url":"https://api.github.com/repos/RESMIND/VitiScanPRO_V3/releases{/id}","deployments_url":"https://api.github.com/repos/RESMIND/VitiScanPRO_V3/deployments"},"head_repository":{"id":1151853619,"node_id":"R_kgDORKfkMw","name":"VitiScanPRO_V3","full_name":"RESMIND/VitiScanPRO_V3","private":false,"owner":{"login":"RESMIND","id":212447599,"node_id":"U_kgDODKmxbw","avatar_url":"https://avatars.githubusercontent.com/u/212447599?v=4","gravatar_id":"","url":"https://api.github.com/users/RESMIND","html_url":"https://github.com/RESMIND","followers_url":"https://api.github.com/users/RESMIND/followers","following_url":"https://api.github.com/users/RESMIND/following{/other_user}","gists_url":"https://api.github.com/users/RESMIND/gists{/gist_id}","starred_url":"https://api.github.com/users/RESMIND/starred{/owner}{/repo}","subscriptions_url":"https://api.github.com/users/RESMIND/subscriptions","organizations_url":"https://api.github.com/users/RESMIND/orgs","repos_url":"https://api.github.com/users/RESMIND/repos","events_url":"https://api.github.com/users/RESMIND/events{/privacy}","received_events_url":"https://api.github.com/users/RESMIND/received_events","type":"User","user_view_type":"public","site_admin":false},"html_url":"https://github.com/RESMIND/VitiScanPRO_V3","description":"Sync local changes cu repo-ul remote","fork":false,"url":"https://api.github.com/repos/RESMIND/VitiScanPRO_V3","forks_url":"https://api.github.com/repos/RESMIND/VitiScanPRO_V3/forks","keys_url":"https://api.github.com/repos/RESMIND/VitiScanPRO_V3/keys{/key_id}","collaborators_url":"https://api.github.com/repos/RESMIND/VitiScanPRO_V3/collaborators{/collaborator}","teams_url":"https://api.github.com/repos/RESMIND/VitiScanPRO_V3/teams","hooks_url":"https://api.github.com/repos/RESMIND/VitiScanPRO_V3/hooks","issue_events_url":"https://api.github.com/repos/RESMIND/VitiScanPRO_V3/issues/events{/number}","events_url":"https://api.github.com/repos/RESMIND/VitiScanPRO_V3/events","assignees_url":"https://api.github.com/repos/RESMIND/VitiScanPRO_V3/assignees{/user}","branches_url":"https://api.github.com/repos/RESMIND/VitiScanPRO_V3/branches{/branch}","tags_url":"https://api.github.com/repos/RESMIND/VitiScanPRO_V3/tags","blobs_url":"https://api.github.com/repos/RESMIND/VitiScanPRO_V3/git/blobs{/sha}","git_tags_url":"https://api.github.com/repos/RESMIND/VitiScanPRO_V3/git/tags{/sha}","git_refs_url":"https://api.github.com/repos/RESMIND/VitiScanPRO_V3/git/refs{/sha}","trees_url":"https://api.github.com/repos/RESMIND/VitiScanPRO_V3/git/trees{/sha}","statuses_url":"https://api.github.com/repos/RESMIND/VitiScanPRO_V3/statuses/{sha}","languages_url":"https://api.github.com/repos/RESMIND/VitiScanPRO_V3/languages","stargazers_url":"https://api.github.com/repos/RESMIND/VitiScanPRO_V3/stargazers","contributors_url":"https://api.github.com/repos/RESMIND/VitiScanPRO_V3/contributors","subscribers_url":"https://api.github.com/repos/RESMIND/VitiScanPRO_V3/subscribers","subscription_url":"https://api.github.com/repos/RESMIND/VitiScanPRO_V3/subscription","commits_url":"https://api.github.com/repos/RESMIND/VitiScanPRO_V3/commits{/sha}","git_commits_url":"https://api.github.com/repos/RESMIND/VitiScanPRO_V3/git/commits{/sha}","comments_url":"https://api.github.com/repos/RESMIND/VitiScanPRO_V3/comments{/number}","issue_comment_url":"https://api.github.com/repos/RESMIND/VitiScanPRO_V3/issues/comments{/number}","contents_url":"https://api.github.com/repos/RESMIND/VitiScanPRO_V3/contents/{+path}","compare_url":"https://api.github.com/repos/RESMIND/VitiScanPRO_V3/compare/{base}...{head}","merges_url":"https://api.github.com/repos/RESMIND/VitiScanPRO_V3/merges","archive_url":"https://api.github.com/repos/RESMIND/VitiScanPRO_V3/{archive_format}{/ref}","downloads_url":"https://api.github.com/repos/RESMIND/VitiScanPRO_V3/downloads","issues_url":"https://api.github.com/repos/RESMIND/VitiScanPRO_V3/issues{/number}","pulls_url":"https://api.github.com/repos/RESMIND/VitiScanPRO_V3/pulls{/number}","milestones_url":"https://api.github.com/repos/RESMIND/VitiScanPRO_V3/milestones{/number}","notifications_url":"https://api.github.com/repos/RESMIND/VitiScanPRO_V3/notifications{?since,all,participating}","labels_url":"https://api.github.com/repos/RESMIND/VitiScanPRO_V3/labels{/name}","releases_url":"https://api.github.com/repos/RESMIND/VitiScanPRO_V3/releases{/id}","deployments_url":"https://api.github.com/repos/RESMIND/VitiScanPRO_V3/deployments"}},{"id":21797856528,"name":"CI","node_id":"WFR_kwLORKfkM88AAAAFE0DlEA","head_branch":"master","head_sha":"37e151c8fd244ab442df30831f51a857d5d2439b","path":".github/workflows/ci.yml","display_title":"ci: add MongoDB service and wait step for backend tests","run_number":12,"event":"push","status":"completed","conclusion":"failure","workflow_id":231456082,"check_suite_id":56761482610,"check_suite_node_id":"CS_kwDORKfkM88AAAANNz99cg","url":"https://api.github.com/repos/RESMIND/VitiScanPRO_V3/actions/runs/21797856528","html_url":"https://github.com/RESMIND/VitiScanPRO_V3/actions/runs/21797856528","pull_requests":[],"created_at":"2026-02-08T12:05:55Z","updated_at":"2026-02-08T12:07:09Z","actor":{"login":"RESMIND","id":212447599,"node_id":"U_kgDODKmxbw","avatar_url":"https://avatars.githubusercontent.com/u/212447599?v=4","gravatar_id":"","url":"https://api.github.com/users/RESMIND","html_url":"https://github.com/RESMIND","followers_url":"https://api.github.com/users/RESMIND/followers","following_url":"https://api.github.com/users/RESMIND/following{/other_user}","gists_url":"https://api.github.com/users/RESMIND/gists{/gist_id}","starred_url":"https://api.github.com/users/RESMIND/starred{/owner}{/repo}","subscriptions_url":"https://api.github.com/users/RESMIND/subscriptions","organizations_url":"https://api.github.com/users/RESMIND/orgs","repos_url":"https://api.github.com/users/RESMIND/repos","events_url":"https://api.github.com/users/RESMIND/events{/privacy}","received_events_url":"https://api.github.com/users/RESMIND/received_events","type":"User","user_view_type":"public","site_admin":false},"run_attempt":1,"referenced_workflows":[],"run_started_at":"2026-02-08T12:05:55Z","triggering_actor":{"login":"RESMIND","id":212447599,"node_id":"U_kgDODKmxbw","avatar_url":"https://avatars.githubusercontent.com/u/212447599?v=4","gravatar_id":"","url":"https://api.github.com/users/RESMIND","html_url":"https://github.com/RESMIND","followers_url":"https://api.github.com/users/RESMIND/followers","following_url":"https://api.github.com/users/RESMIND/following{/other_user}","gists_url":"https://api.github.com/users/RESMIND/gists{/gist_id}","starred_url":"https://api.github.com/users/RESMIND/starred{/owner}{/repo}","subscriptions_url":"https://api.github.com/users/RESMIND/subscriptions","organizations_url":"https://api.github.com/users/RESMIND/orgs","repos_url":"https://api.github.com/users/RESMIND/repos","events_url":"https://api.github.com/users/RESMIND/events{/privacy}","received_events_url":"https://api.github.com/users/RESMIND/received_events","type":"User","user_view_type":"public","site_admin":false},"jobs_url":"https://api.github.com/repos/RESMIND/VitiScanPRO_V3/actions/runs/21797856528/jobs","logs_url":"https://api.github.com/repos/RESMIND/VitiScanPRO_V3/actions/runs/21797856528/logs","check_suite_url":"https://api.github.com/repos/RESMIND/VitiScanPRO_V3/check-suites/56761482610","artifacts_url":"https://api.github.com/repos/RESMIND/VitiScanPRO_V3/actions/runs/21797856528/artifacts","cancel_url":"https://api.github.com/repos/RESMIND/VitiScanPRO_V3/actions/runs/21797856528/cancel","rerun_url":"https://api.github.com/repos/RESMIND/VitiScanPRO_V3/actions/runs/21797856528/rerun","previous_attempt_url":null,"workflow_url":"https://api.github.com/repos/RESMIND/VitiScanPRO_V3/actions/workflows/231456082","head_commit":{"id":"37e151c8fd244ab442df30831f51a857d5d2439b","tree_id":"bfb7bc6f83fa766cf69a3d1033abe47a36f76e35","message":"ci: add MongoDB service and wait step for backend tests","timestamp":"2026-02-08T12:05:51Z","author":{"name":"VitiScan Bot","email":"dev@vitiscan.local"},"committer":{"name":"VitiScan Bot","email":"dev@vitiscan.local"}},"repository":{"id":1151853619,"node_id":"R_kgDORKfkMw","name":"VitiScanPRO_V3","full_name":"RESMIND/VitiScanPRO_V3","private":false,"owner":{"login":"RESMIND","id":212447599,"node_id":"U_kgDODKmxbw","avatar_url":"https://avatars.githubusercontent.com/u/212447599?v=4","gravatar_id":"","url":"https://api.github.com/users/RESMIND","html_url":"https://github.com/RESMIND","followers_url":"https://api.github.com/users/RESMIND/followers","following_url":"https://api.github.com/users/RESMIND/following{/other_user}","gists_url":"https://api.github.com/users/RESMIND/gists{/gist_id}","starred_url":"https://api.github.com/users/RESMIND/starred{/owner}{/repo}","subscriptions_url":"https://api.github.com/users/RESMIND/subscriptions","organizations_url":"https://api.github.com/users/RESMIND/orgs","repos_url":"https://api.github.com/users/RESMIND/repos","events_url":"https://api.github.com/users/RESMIND/events{/privacy}","received_events_url":"https://api.github.com/users/RESMIND/received_events","type":"User","user_view_type":"public","site_admin":false},"html_url":"https://github.com/RESMIND/VitiScanPRO_V3","description":"Sync local changes cu repo-ul remote","fork":false,"url":"https://api.github.com/repos/RESMIND/VitiScanPRO_V3","forks_url":"https://api.github.com/repos/RESMIND/VitiScanPRO_V3/forks","keys_url":"https://api.github.com/repos/RESMIND/VitiScanPRO_V3/keys{/key_id}","collaborators_url":"https://api.github.com/repos/RESMIND/VitiScanPRO_V3/collaborators{/collaborator}","teams_url":"https://api.github.com/repos/RESMIND/VitiScanPRO_V3/teams","hooks_url":"https://api.github.com/repos/RESMIND/VitiScanPRO_V3/hooks","issue_events_url":"https://api.github.com/repos/RESMIND/VitiScanPRO_V3/issues/events{/number}","events_url":"https://api.github.com/repos/RESMIND/VitiScanPRO_V3/events","assignees_url":"https://api.github.com/repos/RESMIND/VitiScanPRO_V3/assignees{/user}","branches_url":"https://api.github.com/repos/RESMIND/VitiScanPRO_V3/branches{/branch}","tags_url":"https://api.github.com/repos/RESMIND/VitiScanPRO_V3/tags","blobs_url":"https://api.github.com/repos/RESMIND/VitiScanPRO_V3/git/blobs{/sha}","git_tags_url":"https://api.github.com/repos/RESMIND/VitiScanPRO_V3/git/tags{/sha}","git_refs_url":"https://api.github.com/repos/RESMIND/VitiScanPRO_V3/git/refs{/sha}","trees_url":"https://api.github.com/repos/RESMIND/VitiScanPRO_V3/git/trees{/sha}","statuses_url":"https://api.github.com/repos/RESMIND/VitiScanPRO_V3/statuses/{sha}","languages_url":"https://api.github.com/repos/RESMIND/VitiScanPRO_V3/languages","stargazers_url":"https://api.github.com/repos/RESMIND/VitiScanPRO_V3/stargazers","contributors_url":"https://api.github.com/repos/RESMIND/VitiScanPRO_V3/contributors","subscribers_url":"https://api.github.com/repos/RESMIND/VitiScanPRO_V3/subscribers","subscription_url":"https://api.github.com/repos/RESMIND/VitiScanPRO_V3/subscription","commits_url":"https://api.github.com/repos/RESMIND/VitiScanPRO_V3/commits{/sha}","git_commits_url":"https://api.github.com/repos/RESMIND/VitiScanPRO_V3/git/commits{/sha}","comments_url":"https://api.github.com/repos/RESMIND/VitiScanPRO_V3/comments{/number}","issue_comment_url":"https://api.github.com/repos/RESMIND/VitiScanPRO_V3/issues/comments{/number}","contents_url":"https://api.github.com/repos/RESMIND/VitiScanPRO_V3/contents/{+path}","compare_url":"https://api.github.com/repos/RESMIND/VitiScanPRO_V3/compare/{base}...{head}","merges_url":"https://api.github.com/repos/RESMIND/VitiScanPRO_V3/merges","archive_url":"https://api.github.com/repos/RESMIND/VitiScanPRO_V3/{archive_format}{/ref}","downloads_url":"https://api.github.com/repos/RESMIND/VitiScanPRO_V3/downloads","issues_url":"https://api.github.com/repos/RESMIND/VitiScanPRO_V3/issues{/number}","pulls_url":"https://api.github.com/repos/RESMIND/VitiScanPRO_V3/pulls{/number}","milestones_url":"https://api.github.com/repos/RESMIND/VitiScanPRO_V3/milestones{/number}","notifications_url":"https://api.github.com/repos/RESMIND/VitiScanPRO_V3/notifications{?since,all,participating}","labels_url":"https://api.github.com/repos/RESMIND/VitiScanPRO_V3/labels{/name}","releases_url":"https://api.github.com/repos/RESMIND/VitiScanPRO_V3/releases{/id}","deployments_url":"https://api.github.com/repos/RESMIND/VitiScanPRO_V3/deployments"},"head_repository":{"id":1151853619,"node_id":"R_kgDORKfkMw","name":"VitiScanPRO_V3","full_name":"RESMIND/VitiScanPRO_V3","private":false,"owner":{"login":"RESMIND","id":212447599,"node_id":"U_kgDODKmxbw","avatar_url":"https://avatars.githubusercontent.com/u/212447599?v=4","gravatar_id":"","url":"https://api.github.com/users/RESMIND","html_url":"https://github.com/RESMIND","followers_url":"https://api.github.com/users/RESMIND/followers","following_url":"https://api.github.com/users/RESMIND/following{/other_user}","gists_url":"https://api.github.com/users/RESMIND/gists{/gist_id}","starred_url":"https://api.github.com/users/RESMIND/starred{/owner}{/repo}","subscriptions_url":"https://api.github.com/users/RESMIND/subscriptions","organizations_url":"https://api.github.com/users/RESMIND/orgs","repos_url":"https://api.github.com/users/RESMIND/repos","events_url":"https://api.github.com/users/RESMIND/events{/privacy}","received_events_url":"https://api.github.com/users/RESMIND/received_events","type":"User","user_view_type":"public","site_admin":false},"html_url":"https://github.com/RESMIND/VitiScanPRO_V3","description":"Sync local changes cu repo-ul remote","fork":false,"url":"https://api.github.com/repos/RESMIND/VitiScanPRO_V3","forks_url":"https://api.github.com/repos/RESMIND/VitiScanPRO_V3/forks","keys_url":"https://api.github.com/repos/RESMIND/VitiScanPRO_V3/keys{/key_id}","collaborators_url":"https://api.github.com/repos/RESMIND/VitiScanPRO_V3/collaborators{/collaborator}","teams_url":"https://api.github.com/repos/RESMIND/VitiScanPRO_V3/teams","hooks_url":"https://api.github.com/repos/RESMIND/VitiScanPRO_V3/hooks","issue_events_url":"https://api.github.com/repos/RESMIND/VitiScanPRO_V3/issues/events{/number}","events_url":"https://api.github.com/repos/RESMIND/VitiScanPRO_V3/events","assignees_url":"https://api.github.com/repos/RESMIND/VitiScanPRO_V3/assignees{/user}","branches_url":"https://api.github.com/repos/RESMIND/VitiScanPRO_V3/branches{/branch}","tags_url":"https://api.github.com/repos/RESMIND/VitiScanPRO_V3/tags","blobs_url":"https://api.github.com/repos/RESMIND/VitiScanPRO_V3/git/blobs{/sha}","git_tags_url":"https://api.github.com/repos/RESMIND/VitiScanPRO_V3/git/tags{/sha}","git_refs_url":"https://api.github.com/repos/RESMIND/VitiScanPRO_V3/git/refs{/sha}","trees_url":"https://api.github.com/repos/RESMIND/VitiScanPRO_V3/git/trees{/sha}","statuses_url":"https://api.github.com/repos/RESMIND/VitiScanPRO_V3/statuses/{sha}","languages_url":"https://api.github.com/repos/RESMIND/VitiScanPRO_V3/languages","stargazers_url":"https://api.github.com/repos/RESMIND/VitiScanPRO_V3/stargazers","contributors_url":"https://api.github.com/repos/RESMIND/VitiScanPRO_V3/contributors","subscribers_url":"https://api.github.com/repos/RESMIND/VitiScanPRO_V3/subscribers","subscription_url":"https://api.github.com/repos/RESMIND/VitiScanPRO_V3/subscription","commits_url":"https://api.github.com/repos/RESMIND/VitiScanPRO_V3/commits{/sha}","git_commits_url":"https://api.github.com/repos/RESMIND/VitiScanPRO_V3/git/commits{/sha}","comments_url":"https://api.github.com/repos/RESMIND/VitiScanPRO_V3/comments{/number}","issue_comment_url":"https://api.github.com/repos/RESMIND/VitiScanPRO_V3/issues/comments{/number}","contents_url":"https://api.github.com/repos/RESMIND/VitiScanPRO_V3/contents/{+path}","compare_url":"https://api.github.com/repos/RESMIND/VitiScanPRO_V3/compare/{base}...{head}","merges_url":"https://api.github.com/repos/RESMIND/VitiScanPRO_V3/merges","archive_url":"https://api.github.com/repos/RESMIND/VitiScanPRO_V3/{archive_format}{/ref}","downloads_url":"https://api.github.com/repos/RESMIND/VitiScanPRO_V3/downloads","issues_url":"https://api.github.com/repos/RESMIND/VitiScanPRO_V3/issues{/number}","pulls_url":"https://api.github.com/repos/RESMIND/VitiScanPRO_V3/pulls{/number}","milestones_url":"https://api.github.com/repos/RESMIND/VitiScanPRO_V3/milestones{/number}","notifications_url":"https://api.github.com/repos/RESMIND/VitiScanPRO_V3/notifications{?since,all,participating}","labels_url":"https://api.github.com/repos/RESMIND/VitiScanPRO_V3/labels{/name}","releases_url":"https://api.github.com/repos/RESMIND/VitiScanPRO_V3/releases{/id}","deployments_url":"https://api.github.com/repos/RESMIND/VitiScanPRO_V3/deployments"}},{"id":21797127655,"name":"CI","node_id":"WFR_kwLORKfkM88AAAAFEzXF5w","head_branch":"master","head_sha":"a7e65f1e0b1aa2431af26d1adf524671cf5f8c66","path":".github/workflows/ci.yml","display_title":"chore(ci): trigger CI on master as well as main","run_number":11,"event":"push","status":"completed","conclusion":"failure","workflow_id":231456082,"check_suite_id":56759514707,"check_suite_node_id":"CS_kwDORKfkM88AAAANNyF2Uw","url":"https://api.github.com/repos/RESMIND/VitiScanPRO_V3/actions/runs/21797127655","html_url":"https://github.com/RESMIND/VitiScanPRO_V3/actions/runs/21797127655","pull_requests":[],"created_at":"2026-02-08T11:08:10Z","updated_at":"2026-02-08T11:24:45Z","actor":{"login":"RESMIND","id":212447599,"node_id":"U_kgDODKmxbw","avatar_url":"https://avatars.githubusercontent.com/u/212447599?v=4","gravatar_id":"","url":"https://api.github.com/users/RESMIND","html_url":"https://github.com/RESMIND","followers_url":"https://api.github.com/users/RESMIND/followers","following_url":"https://api.github.com/users/RESMIND/following{/other_user}","gists_url":"https://api.github.com/users/RESMIND/gists{/gist_id}","starred_url":"https://api.github.com/users/RESMIND/starred{/owner}{/repo}","subscriptions_url":"https://api.github.com/users/RESMIND/subscriptions","organizations_url":"https://api.github.com/users/RESMIND/orgs","repos_url":"https://api.github.com/users/RESMIND/repos","events_url":"https://api.github.com/users/RESMIND/events{/privacy}","received_events_url":"https://api.github.com/users/RESMIND/received_events","type":"User","user_view_type":"public","site_admin":false},"run_attempt":1,"referenced_workflows":[],"run_started_at":"2026-02-08T11:08:10Z","triggering_actor":{"login":"RESMIND","id":212447599,"node_id":"U_kgDODKmxbw","avatar_url":"https://avatars.githubusercontent.com/u/212447599?v=4","gravatar_id":"","url":"https://api.github.com/users/RESMIND","html_url":"https://github.com/RESMIND","followers_url":"https://api.github.com/users/RESMIND/followers","following_url":"https://api.github.com/users/RESMIND/following{/other_user}","gists_url":"https://api.github.com/users/RESMIND/gists{/gist_id}","starred_url":"https://api.github.com/users/RESMIND/starred{/owner}{/repo}","subscriptions_url":"https://api.github.com/users/RESMIND/subscriptions","organizations_url":"https://api.github.com/users/RESMIND/orgs","repos_url":"https://api.github.com/users/RESMIND/repos","events_url":"https://api.github.com/users/RESMIND/events{/privacy}","received_events_url":"https://api.github.com/users/RESMIND/received_events","type":"User","user_view_type":"public","site_admin":false},"jobs_url":"https://api.github.com/repos/RESMIND/VitiScanPRO_V3/actions/runs/21797127655/jobs","logs_url":"https://api.github.com/repos/RESMIND/VitiScanPRO_V3/actions/runs/21797127655/logs","check_suite_url":"https://api.github.com/repos/RESMIND/VitiScanPRO_V3/check-suites/56759514707","artifacts_url":"https://api.github.com/repos/RESMIND/VitiScanPRO_V3/actions/runs/21797127655/artifacts","cancel_url":"https://api.github.com/repos/RESMIND/VitiScanPRO_V3/actions/runs/21797127655/cancel","rerun_url":"https://api.github.com/repos/RESMIND/VitiScanPRO_V3/actions/runs/21797127655/rerun","previous_attempt_url":null,"workflow_url":"https://api.github.com/repos/RESMIND/VitiScanPRO_V3/actions/workflows/231456082","head_commit":{"id":"a7e65f1e0b1aa2431af26d1adf524671cf5f8c66","tree_id":"2120e7e651488028ef94b85d63a6785535b3d30d","message":"chore(ci): trigger CI on master as well as main","timestamp":"2026-02-08T11:08:06Z","author":{"name":"VitiScan Bot","email":"dev@vitiscan.local"},"committer":{"name":"VitiScan Bot","email":"dev@vitiscan.local"}},"repository":{"id":1151853619,"node_id":"R_kgDORKfkMw","name":"VitiScanPRO_V3","full_name":"RESMIND/VitiScanPRO_V3","private":false,"owner":{"login":"RESMIND","id":212447599,"node_id":"U_kgDODKmxbw","avatar_url":"https://avatars.githubusercontent.com/u/212447599?v=4","gravatar_id":"","url":"https://api.github.com/users/RESMIND","html_url":"https://github.com/RESMIND","followers_url":"https://api.github.com/users/RESMIND/followers","following_url":"https://api.github.com/users/RESMIND/following{/other_user}","gists_url":"https://api.github.com/users/RESMIND/gists{/gist_id}","starred_url":"https://api.github.com/users/RESMIND/starred{/owner}{/repo}","subscriptions_url":"https://api.github.com/users/RESMIND/subscriptions","organizations_url":"https://api.github.com/users/RESMIND/orgs","repos_url":"https://api.github.com/users/RESMIND/repos","events_url":"https://api.github.com/users/RESMIND/events{/privacy}","received_events_url":"https://api.github.com/users/RESMIND/received_events","type":"User","user_view_type":"public","site_admin":false},"html_url":"https://github.com/RESMIND/VitiScanPRO_V3","description":"Sync local changes cu repo-ul remote","fork":false,"url":"https://api.github.com/repos/RESMIND/VitiScanPRO_V3","forks_url":"https://api.github.com/repos/RESMIND/VitiScanPRO_V3/forks","keys_url":"https://api.github.com/repos/RESMIND/VitiScanPRO_V3/keys{/key_id}","collaborators_url":"https://api.github.com/repos/RESMIND/VitiScanPRO_V3/collaborators{/collaborator}","teams_url":"https://api.github.com/repos/RESMIND/VitiScanPRO_V3/teams","hooks_url":"https://api.github.com/repos/RESMIND/VitiScanPRO_V3/hooks","issue_events_url":"https://api.github.com/repos/RESMIND/VitiScanPRO_V3/issues/events{/number}","events_url":"https://api.github.com/repos/RESMIND/VitiScanPRO_V3/events","assignees_url":"https://api.github.com/repos/RESMIND/VitiScanPRO_V3/assignees{/user}","branches_url":"https://api.github.com/repos/RESMIND/VitiScanPRO_V3/branches{/branch}","tags_url":"https://api.github.com/repos/RESMIND/VitiScanPRO_V3/tags","blobs_url":"https://api.github.com/repos/RESMIND/VitiScanPRO_V3/git/blobs{/sha}","git_tags_url":"https://api.github.com/repos/RESMIND/VitiScanPRO_V3/git/tags{/sha}","git_refs_url":"https://api.github.com/repos/RESMIND/VitiScanPRO_V3/git/refs{/sha}","trees_url":"https://api.github.com/repos/RESMIND/VitiScanPRO_V3/git/trees{/sha}","statuses_url":"https://api.github.com/repos/RESMIND/VitiScanPRO_V3/statuses/{sha}","languages_url":"https://api.github.com/repos/RESMIND/VitiScanPRO_V3/languages","stargazers_url":"https://api.github.com/repos/RESMIND/VitiScanPRO_V3/stargazers","contributors_url":"https://api.github.com/repos/RESMIND/VitiScanPRO_V3/contributors","subscribers_url":"https://api.github.com/repos/RESMIND/VitiScanPRO_V3/subscribers","subscription_url":"https://api.github.com/repos/RESMIND/VitiScanPRO_V3/subscription","commits_url":"https://api.github.com/repos/RESMIND/VitiScanPRO_V3/commits{/sha}","git_commits_url":"https://api.github.com/repos/RESMIND/VitiScanPRO_V3/git/commits{/sha}","comments_url":"https://api.github.com/repos/RESMIND/VitiScanPRO_V3/comments{/number}","issue_comment_url":"https://api.github.com/repos/RESMIND/VitiScanPRO_V3/issues/comments{/number}","contents_url":"https://api.github.com/repos/RESMIND/VitiScanPRO_V3/contents/{+path}","compare_url":"https://api.github.com/repos/RESMIND/VitiScanPRO_V3/compare/{base}...{head}","merges_url":"https://api.github.com/repos/RESMIND/VitiScanPRO_V3/merges","archive_url":"https://api.github.com/repos/RESMIND/VitiScanPRO_V3/{archive_format}{/ref}","downloads_url":"https://api.github.com/repos/RESMIND/VitiScanPRO_V3/downloads","issues_url":"https://api.github.com/repos/RESMIND/VitiScanPRO_V3/issues{/number}","pulls_url":"https://api.github.com/repos/RESMIND/VitiScanPRO_V3/pulls{/number}","milestones_url":"https://api.github.com/repos/RESMIND/VitiScanPRO_V3/milestones{/number}","notifications_url":"https://api.github.com/repos/RESMIND/VitiScanPRO_V3/notifications{?since,all,participating}","labels_url":"https://api.github.com/repos/RESMIND/VitiScanPRO_V3/labels{/name}","releases_url":"https://api.github.com/repos/RESMIND/VitiScanPRO_V3/releases{/id}","deployments_url":"https://api.github.com/repos/RESMIND/VitiScanPRO_V3/deployments"},"head_repository":{"id":1151853619,"node_id":"R_kgDORKfkMw","name":"VitiScanPRO_V3","full_name":"RESMIND/VitiScanPRO_V3","private":false,"owner":{"login":"RESMIND","id":212447599,"node_id":"U_kgDODKmxbw","avatar_url":"https://avatars.githubusercontent.com/u/212447599?v=4","gravatar_id":"","url":"https://api.github.com/users/RESMIND","html_url":"https://github.com/RESMIND","followers_url":"https://api.github.com/users/RESMIND/followers","following_url":"https://api.github.com/users/RESMIND/following{/other_user}","gists_url":"https://api.github.com/users/RESMIND/gists{/gist_id}","starred_url":"https://api.github.com/users/RESMIND/starred{/owner}{/repo}","subscriptions_url":"https://api.github.com/users/RESMIND/subscriptions","organizations_url":"https://api.github.com/users/RESMIND/orgs","repos_url":"https://api.github.com/users/RESMIND/repos","events_url":"https://api.github.com/users/RESMIND/events{/privacy}","received_events_url":"https://api.github.com/users/RESMIND/received_events","type":"User","user_view_type":"public","site_admin":false},"html_url":"https://github.com/RESMIND/VitiScanPRO_V3","description":"Sync local changes cu repo-ul remote","fork":false,"url":"https://api.github.com/repos/RESMIND/VitiScanPRO_V3","forks_url":"https://api.github.com/repos/RESMIND/VitiScanPRO_V3/forks","keys_url":"https://api.github.com/repos/RESMIND/VitiScanPRO_V3/keys{/key_id}","collaborators_url":"https://api.github.com/repos/RESMIND/VitiScanPRO_V3/collaborators{/collaborator}","teams_url":"https://api.github.com/repos/RESMIND/VitiScanPRO_V3/teams","hooks_url":"https://api.github.com/repos/RESMIND/VitiScanPRO_V3/hooks","issue_events_url":"https://api.github.com/repos/RESMIND/VitiScanPRO_V3/issues/events{/number}","events_url":"https://api.github.com/repos/RESMIND/VitiScanPRO_V3/events","assignees_url":"https://api.github.com/repos/RESMIND/VitiScanPRO_V3/assignees{/user}","branches_url":"https://api.github.com/repos/RESMIND/VitiScanPRO_V3/branches{/branch}","tags_url":"https://api.github.com/repos/RESMIND/VitiScanPRO_V3/tags","blobs_url":"https://api.github.com/repos/RESMIND/VitiScanPRO_V3/git/blobs{/sha}","git_tags_url":"https://api.github.com/repos/RESMIND/VitiScanPRO_V3/git/tags{/sha}","git_refs_url":"https://api.github.com/repos/RESMIND/VitiScanPRO_V3/git/refs{/sha}","trees_url":"https://api.github.com/repos/RESMIND/VitiScanPRO_V3/git/trees{/sha}","statuses_url":"https://api.github.com/repos/RESMIND/VitiScanPRO_V3/statuses/{sha}","languages_url":"https://api.github.com/repos/RESMIND/VitiScanPRO_V3/languages","stargazers_url":"https://api.github.com/repos/RESMIND/VitiScanPRO_V3/stargazers","contributors_url":"https://api.github.com/repos/RESMIND/VitiScanPRO_V3/contributors","subscribers_url":"https://api.github.com/repos/RESMIND/VitiScanPRO_V3/subscribers","subscription_url":"https://api.github.com/repos/RESMIND/VitiScanPRO_V3/subscription","commits_url":"https://api.github.com/repos/RESMIND/VitiScanPRO_V3/commits{/sha}","git_commits_url":"https://api.github.com/repos/RESMIND/VitiScanPRO_V3/git/commits{/sha}","comments_url":"https://api.github.com/repos/RESMIND/VitiScanPRO_V3/comments{/number}","issue_comment_url":"https://api.github.com/repos/RESMIND/VitiScanPRO_V3/issues/comments{/number}","contents_url":"https://api.github.com/repos/RESMIND/VitiScanPRO_V3/contents/{+path}","compare_url":"https://api.github.com/repos/RESMIND/VitiScanPRO_V3/compare/{base}...{head}","merges_url":"https://api.github.com/repos/RESMIND/VitiScanPRO_V3/merges","archive_url":"https://api.github.com/repos/RESMIND/VitiScanPRO_V3/{archive_format}{/ref}","downloads_url":"https://api.github.com/repos/RESMIND/VitiScanPRO_V3/downloads","issues_url":"https://api.github.com/repos/RESMIND/VitiScanPRO_V3/issues{/number}","pulls_url":"https://api.github.com/repos/RESMIND/VitiScanPRO_V3/pulls{/number}","milestones_url":"https://api.github.com/repos/RESMIND/VitiScanPRO_V3/milestones{/number}","notifications_url":"https://api.github.com/repos/RESMIND/VitiScanPRO_V3/notifications{?since,all,participating}","labels_url":"https://api.github.com/repos/RESMIND/VitiScanPRO_V3/labels{/name}","releases_url":"https://api.github.com/repos/RESMIND/VitiScanPRO_V3/releases{/id}","deployments_url":"https://api.github.com/repos/RESMIND/VitiScanPRO_V3/deployments"}},{"id":21782098464,"name":".github/workflows/ci.yml","node_id":"WFR_kwLORKfkM88AAAAFElByIA","head_branch":"master","head_sha":"4adcbf36ad0faa17a02ca3be7cfee2619f23ea97","path":".github/workflows/ci.yml","display_title":"chore: add CI workflow to master branch","run_number":10,"event":"push","status":"completed","conclusion":"failure","workflow_id":231456082,"check_suite_id":56712298343,"check_suite_node_id":"CS_kwDORKfkM88AAAANNFD_Zw","url":"https://api.github.com/repos/RESMIND/VitiScanPRO_V3/actions/runs/21782098464","html_url":"https://github.com/RESMIND/VitiScanPRO_V3/actions/runs/21782098464","pull_requests":[],"created_at":"2026-02-07T15:07:46Z","updated_at":"2026-02-07T15:07:46Z","actor":{"login":"RESMIND","id":212447599,"node_id":"U_kgDODKmxbw","avatar_url":"https://avatars.githubusercontent.com/u/212447599?v=4","gravatar_id":"","url":"https://api.github.com/users/RESMIND","html_url":"https://github.com/RESMIND","followers_url":"https://api.github.com/users/RESMIND/followers","following_url":"https://api.github.com/users/RESMIND/following{/other_user}","gists_url":"https://api.github.com/users/RESMIND/gists{/gist_id}","starred_url":"https://api.github.com/users/RESMIND/starred{/owner}{/repo}","subscriptions_url":"https://api.github.com/users/RESMIND/subscriptions","organizations_url":"https://api.github.com/users/RESMIND/orgs","repos_url":"https://api.github.com/users/RESMIND/repos","events_url":"https://api.github.com/users/RESMIND/events{/privacy}","received_events_url":"https://api.github.com/users/RESMIND/received_events","type":"User","user_view_type":"public","site_admin":false},"run_attempt":1,"referenced_workflows":[],"run_started_at":"2026-02-07T15:07:46Z","triggering_actor":{"login":"RESMIND","id":212447599,"node_id":"U_kgDODKmxbw","avatar_url":"https://avatars.githubusercontent.com/u/212447599?v=4","gravatar_id":"","url":"https://api.github.com/users/RESMIND","html_url":"https://github.com/RESMIND","followers_url":"https://api.github.com/users/RESMIND/followers","following_url":"https://api.github.com/users/RESMIND/following{/other_user}","gists_url":"https://api.github.com/users/RESMIND/gists{/gist_id}","starred_url":"https://api.github.com/users/RESMIND/starred{/owner}{/repo}","subscriptions_url":"https://api.github.com/users/RESMIND/subscriptions","organizations_url":"https://api.github.com/users/RESMIND/orgs","repos_url":"https://api.github.com/users/RESMIND/repos","events_url":"https://api.github.com/users/RESMIND/events{/privacy}","received_events_url":"https://api.github.com/users/RESMIND/received_events","type":"User","user_view_type":"public","site_admin":false},"jobs_url":"https://api.github.com/repos/RESMIND/VitiScanPRO_V3/actions/runs/21782098464/jobs","logs_url":"https://api.github.com/repos/RESMIND/VitiScanPRO_V3/actions/runs/21782098464/logs","check_suite_url":"https://api.github.com/repos/RESMIND/VitiScanPRO_V3/check-suites/56712298343","artifacts_url":"https://api.github.com/repos/RESMIND/VitiScanPRO_V3/actions/runs/21782098464/artifacts","cancel_url":"https://api.github.com/repos/RESMIND/VitiScanPRO_V3/actions/runs/21782098464/cancel","rerun_url":"https://api.github.com/repos/RESMIND/VitiScanPRO_V3/actions/runs/21782098464/rerun","previous_attempt_url":null,"workflow_url":"https://api.github.com/repos/RESMIND/VitiScanPRO_V3/actions/workflows/231456082","head_commit":{"id":"4adcbf36ad0faa17a02ca3be7cfee2619f23ea97","tree_id":"355a30a3e59a9bb1e9d4b46c62eff5a8f8dd2b7e","message":"chore: add CI workflow to master branch","timestamp":"2026-02-07T15:07:36Z","author":{"name":"VitiScan Bot","email":"dev@vitiscan.local"},"committer":{"name":"VitiScan Bot","email":"dev@vitiscan.local"}},"repository":{"id":1151853619,"node_id":"R_kgDORKfkMw","name":"VitiScanPRO_V3","full_name":"RESMIND/VitiScanPRO_V3","private":false,"owner":{"login":"RESMIND","id":212447599,"node_id":"U_kgDODKmxbw","avatar_url":"https://avatars.githubusercontent.com/u/212447599?v=4","gravatar_id":"","url":"https://api.github.com/users/RESMIND","html_url":"https://github.com/RESMIND","followers_url":"https://api.github.com/users/RESMIND/followers","following_url":"https://api.github.com/users/RESMIND/following{/other_user}","gists_url":"https://api.github.com/users/RESMIND/gists{/gist_id}","starred_url":"https://api.github.com/users/RESMIND/starred{/owner}{/repo}","subscriptions_url":"https://api.github.com/users/RESMIND/subscriptions","organizations_url":"https://api.github.com/users/RESMIND/orgs","repos_url":"https://api.github.com/users/RESMIND/repos","events_url":"https://api.github.com/users/RESMIND/events{/privacy}","received_events_url":"https://api.github.com/users/RESMIND/received_events","type":"User","user_view_type":"public","site_admin":false},"html_url":"https://github.com/RESMIND/VitiScanPRO_V3","description":"Sync local changes cu repo-ul remote","fork":false,"url":"https://api.github.com/repos/RESMIND/VitiScanPRO_V3","forks_url":"https://api.github.com/repos/RESMIND/VitiScanPRO_V3/forks","keys_url":"https://api.github.com/repos/RESMIND/VitiScanPRO_V3/keys{/key_id}","collaborators_url":"https://api.github.com/repos/RESMIND/VitiScanPRO_V3/collaborators{/collaborator}","teams_url":"https://api.github.com/repos/RESMIND/VitiScanPRO_V3/teams","hooks_url":"https://api.github.com/repos/RESMIND/VitiScanPRO_V3/hooks","issue_events_url":"https://api.github.com/repos/RESMIND/VitiScanPRO_V3/issues/events{/number}","events_url":"https://api.github.com/repos/RESMIND/VitiScanPRO_V3/events","assignees_url":"https://api.github.com/repos/RESMIND/VitiScanPRO_V3/assignees{/user}","branches_url":"https://api.github.com/repos/RESMIND/VitiScanPRO_V3/branches{/branch}","tags_url":"https://api.github.com/repos/RESMIND/VitiScanPRO_V3/tags","blobs_url":"https://api.github.com/repos/RESMIND/VitiScanPRO_V3/git/blobs{/sha}","git_tags_url":"https://api.github.com/repos/RESMIND/VitiScanPRO_V3/git/tags{/sha}","git_refs_url":"https://api.github.com/repos/RESMIND/VitiScanPRO_V3/git/refs{/sha}","trees_url":"https://api.github.com/repos/RESMIND/VitiScanPRO_V3/git/trees{/sha}","statuses_url":"https://api.github.com/repos/RESMIND/VitiScanPRO_V3/statuses/{sha}","languages_url":"https://api.github.com/repos/RESMIND/VitiScanPRO_V3/languages","stargazers_url":"https://api.github.com/repos/RESMIND/VitiScanPRO_V3/stargazers","contributors_url":"https://api.github.com/repos/RESMIND/VitiScanPRO_V3/contributors","subscribers_url":"https://api.github.com/repos/RESMIND/VitiScanPRO_V3/subscribers","subscription_url":"https://api.github.com/repos/RESMIND/VitiScanPRO_V3/subscription","commits_url":"https://api.github.com/repos/RESMIND/VitiScanPRO_V3/commits{/sha}","git_commits_url":"https://api.github.com/repos/RESMIND/VitiScanPRO_V3/git/commits{/sha}","comments_url":"https://api.github.com/repos/RESMIND/VitiScanPRO_V3/comments{/number}","issue_comment_url":"https://api.github.com/repos/RESMIND/VitiScanPRO_V3/issues/comments{/number}","contents_url":"https://api.github.com/repos/RESMIND/VitiScanPRO_V3/contents/{+path}","compare_url":"https://api.github.com/repos/RESMIND/VitiScanPRO_V3/compare/{base}...{head}","merges_url":"https://api.github.com/repos/RESMIND/VitiScanPRO_V3/merges","archive_url":"https://api.github.com/repos/RESMIND/VitiScanPRO_V3/{archive_format}{/ref}","downloads_url":"https://api.github.com/repos/RESMIND/VitiScanPRO_V3/downloads","issues_url":"https://api.github.com/repos/RESMIND/VitiScanPRO_V3/issues{/number}","pulls_url":"https://api.github.com/repos/RESMIND/VitiScanPRO_V3/pulls{/number}","milestones_url":"https://api.github.com/repos/RESMIND/VitiScanPRO_V3/milestones{/number}","notifications_url":"https://api.github.com/repos/RESMIND/VitiScanPRO_V3/notifications{?since,all,participating}","labels_url":"https://api.github.com/repos/RESMIND/VitiScanPRO_V3/labels{/name}","releases_url":"https://api.github.com/repos/RESMIND/VitiScanPRO_V3/releases{/id}","deployments_url":"https://api.github.com/repos/RESMIND/VitiScanPRO_V3/deployments"},"head_repository":{"id":1151853619,"node_id":"R_kgDORKfkMw","name":"VitiScanPRO_V3","full_name":"RESMIND/VitiScanPRO_V3","private":false,"owner":{"login":"RESMIND","id":212447599,"node_id":"U_kgDODKmxbw","avatar_url":"https://avatars.githubusercontent.com/u/212447599?v=4","gravatar_id":"","url":"https://api.github.com/users/RESMIND","html_url":"https://github.com/RESMIND","followers_url":"https://api.github.com/users/RESMIND/followers","following_url":"https://api.github.com/users/RESMIND/following{/other_user}","gists_url":"https://api.github.com/users/RESMIND/gists{/gist_id}","starred_url":"https://api.github.com/users/RESMIND/starred{/owner}{/repo}","subscriptions_url":"https://api.github.com/users/RESMIND/subscriptions","organizations_url":"https://api.github.com/users/RESMIND/orgs","repos_url":"https://api.github.com/users/RESMIND/repos","events_url":"https://api.github.com/users/RESMIND/events{/privacy}","received_events_url":"https://api.github.com/users/RESMIND/received_events","type":"User","user_view_type":"public","site_admin":false},"html_url":"https://github.com/RESMIND/VitiScanPRO_V3","description":"Sync local changes cu repo-ul remote","fork":false,"url":"https://api.github.com/repos/RESMIND/VitiScanPRO_V3","forks_url":"https://api.github.com/repos/RESMIND/VitiScanPRO_V3/forks","keys_url":"https://api.github.com/repos/RESMIND/VitiScanPRO_V3/keys{/key_id}","collaborators_url":"https://api.github.com/repos/RESMIND/VitiScanPRO_V3/collaborators{/collaborator}","teams_url":"https://api.github.com/repos/RESMIND/VitiScanPRO_V3/teams","hooks_url":"https://api.github.com/repos/RESMIND/VitiScanPRO_V3/hooks","issue_events_url":"https://api.github.com/repos/RESMIND/VitiScanPRO_V3/issues/events{/number}","events_url":"https://api.github.com/repos/RESMIND/VitiScanPRO_V3/events","assignees_url":"https://api.github.com/repos/RESMIND/VitiScanPRO_V3/assignees{/user}","branches_url":"https://api.github.com/repos/RESMIND/VitiScanPRO_V3/branches{/branch}","tags_url":"https://api.github.com/repos/RESMIND/VitiScanPRO_V3/tags","blobs_url":"https://api.github.com/repos/RESMIND/VitiScanPRO_V3/git/blobs{/sha}","git_tags_url":"https://api.github.com/repos/RESMIND/VitiScanPRO_V3/git/tags{/sha}","git_refs_url":"https://api.github.com/repos/RESMIND/VitiScanPRO_V3/git/refs{/sha}","trees_url":"https://api.github.com/repos/RESMIND/VitiScanPRO_V3/git/trees{/sha}","statuses_url":"https://api.github.com/repos/RESMIND/VitiScanPRO_V3/statuses/{sha}","languages_url":"https://api.github.com/repos/RESMIND/VitiScanPRO_V3/languages","stargazers_url":"https://api.github.com/repos/RESMIND/VitiScanPRO_V3/stargazers","contributors_url":"https://api.github.com/repos/RESMIND/VitiScanPRO_V3/contributors","subscribers_url":"https://api.github.com/repos/RESMIND/VitiScanPRO_V3/subscribers","subscription_url":"https://api.github.com/repos/RESMIND/VitiScanPRO_V3/subscription","commits_url":"https://api.github.com/repos/RESMIND/VitiScanPRO_V3/commits{/sha}","git_commits_url":"https://api.github.com/repos/RESMIND/VitiScanPRO_V3/git/commits{/sha}","comments_url":"https://api.github.com/repos/RESMIND/VitiScanPRO_V3/comments{/number}","issue_comment_url":"https://api.github.com/repos/RESMIND/VitiScanPRO_V3/issues/comments{/number}","contents_url":"https://api.github.com/repos/RESMIND/VitiScanPRO_V3/contents/{+path}","compare_url":"https://api.github.com/repos/RESMIND/VitiScanPRO_V3/compare/{base}...{head}","merges_url":"https://api.github.com/repos/RESMIND/VitiScanPRO_V3/merges","archive_url":"https://api.github.com/repos/RESMIND/VitiScanPRO_V3/{archive_format}{/ref}","downloads_url":"https://api.github.com/repos/RESMIND/VitiScanPRO_V3/downloads","issues_url":"https://api.github.com/repos/RESMIND/VitiScanPRO_V3/issues{/number}","pulls_url":"https://api.github.com/repos/RESMIND/VitiScanPRO_V3/pulls{/number}","milestones_url":"https://api.github.com/repos/RESMIND/VitiScanPRO_V3/milestones{/number}","notifications_url":"https://api.github.com/repos/RESMIND/VitiScanPRO_V3/notifications{?since,all,participating}","labels_url":"https://api.github.com/repos/RESMIND/VitiScanPRO_V3/labels{/name}","releases_url":"https://api.github.com/repos/RESMIND/VitiScanPRO_V3/releases{/id}","deployments_url":"https://api.github.com/repos/RESMIND/VitiScanPRO_V3/deployments"}}]}